anypathlib/__init__.py
anypathlib/anypath.py
anypathlib/cli.py
anypathlib/path_handlers/__init__.py
anypathlib/path_handlers/azure_handler.py
anypathlib/path_handlers/base_path_handler.py
anypathlib/path_handlers/local_handler.py
anypathlib/path_handlers/path_types.py
anypathlib/path_handlers/s3_handler.py
AnyPathLib-0.2.0.dist-info/LICENSE
AnyPathLib-0.2.0.dist-info/METADATA
AnyPathLib-0.2.0.dist-info/WHEEL
AnyPathLib-0.2.0.dist-info/entry_points.txt
AnyPathLib-0.2.0.dist-info/top_level.txt
AnyPathLib-0.2.0.dist-info/RECORD
