Metadata-Version: 2.1
Name: AnyPathLib
Version: 0.2.0
Summary: A unified API for every storage resource
Home-page: 
Author: Kfir Goldberg @ WSC-Sports
License: Apache License 2.0
Classifier: Programming Language :: Python :: 3
Classifier: License :: OSI Approved :: Apache Software License
Classifier: Operating System :: OS Independent
Requires-Python: >=3.7
License-File: LICENSE
Requires-Dist: azure-storage-blob (>=12.14.0)
Requires-Dist: azure-identity (>=1.15.0)
Requires-Dist: azure-mgmt-storage (>=21.1.0)
Requires-Dist: boto3 (>=1.34.23)
Requires-Dist: loguru
Requires-Dist: tqdm
Requires-Dist: Click
